odoo/addons/account_bank_statement_import_camt_oca/README.rst
odoo/addons/account_bank_statement_import_camt_oca/__init__.py
odoo/addons/account_bank_statement_import_camt_oca/__manifest__.py
odoo/addons/account_bank_statement_import_camt_oca/i18n/account_bank_statement_import_camt_oca.pot
odoo/addons/account_bank_statement_import_camt_oca/i18n/de.po
odoo/addons/account_bank_statement_import_camt_oca/i18n/es.po
odoo/addons/account_bank_statement_import_camt_oca/i18n/fa.po
odoo/addons/account_bank_statement_import_camt_oca/i18n/fi.po
odoo/addons/account_bank_statement_import_camt_oca/i18n/fr.po
odoo/addons/account_bank_statement_import_camt_oca/i18n/fr_CH.po
odoo/addons/account_bank_statement_import_camt_oca/i18n/gl.po
odoo/addons/account_bank_statement_import_camt_oca/i18n/hr.po
odoo/addons/account_bank_statement_import_camt_oca/i18n/lt_LT.po
odoo/addons/account_bank_statement_import_camt_oca/i18n/nb_NO.po
odoo/addons/account_bank_statement_import_camt_oca/i18n/nl.po
odoo/addons/account_bank_statement_import_camt_oca/i18n/pt_BR.po
odoo/addons/account_bank_statement_import_camt_oca/i18n/pt_PT.po
odoo/addons/account_bank_statement_import_camt_oca/i18n/sl.po
odoo/addons/account_bank_statement_import_camt_oca/models/__init__.py
odoo/addons/account_bank_statement_import_camt_oca/models/account_bank_statement_import.py
odoo/addons/account_bank_statement_import_camt_oca/models/parser.py
odoo/addons/account_bank_statement_import_camt_oca/static/description/icon.png
odoo/addons/account_bank_statement_import_camt_oca/test_files/golden-camt053-no-ntry.pydata
odoo/addons/account_bank_statement_import_camt_oca/test_files/golden-camt053-txdtls.pydata
odoo/addons/account_bank_statement_import_camt_oca/test_files/golden-camt053.pydata
odoo/addons/account_bank_statement_import_camt_oca/test_files/test-camt053
odoo/addons/account_bank_statement_import_camt_oca/test_files/test-camt053-no-ntry
odoo/addons/account_bank_statement_import_camt_oca/test_files/test-camt053-txdtls
odoo11_addon_account_bank_statement_import_camt_oca-11.0.1.1.0.dist-info/METADATA
odoo11_addon_account_bank_statement_import_camt_oca-11.0.1.1.0.dist-info/WHEEL
odoo11_addon_account_bank_statement_import_camt_oca-11.0.1.1.0.dist-info/top_level.txt
odoo11_addon_account_bank_statement_import_camt_oca-11.0.1.1.0.dist-info/RECORD
